{
  "report_type": "decider-daily",
  "generated_at": "2026-05-28T14:40:08Z",
  "run_id": "decider-2026-05-28T14-40",
  "mode": "bau",
  "dryrun": false,

  "pipeline_status": {
    "poller": "No new dome site changes detected this cycle.",
    "analyst": "No new WIN files, no new issue proposals. EXP-436 added (route from ISS-2214: NP.xy cluster post-hoc paragraph hoisting).",
    "curmudgeon": "3 pending reviews processed: WIN-006.c6 (minor_edit), SEC-4.2.4-EXP-434.c2 (no_change, already popped qid-409), WIN-063.c8 (no_change, already popped qid-407)."
  },

  "priority_1_new_wins": {
    "count": 0,
    "action": "none"
  },

  "priority_1b_analyst_proposals": {
    "count": 0,
    "action": "none"
  },

  "priority_2_external_reports": {
    "count": 2,
    "action": "skipped — both already handled: report-1.json is a duplicate stub pointing to canonical; report-1-devilwench-friendly-meta.json has decider_action_needed=false (operator self-comment, no scientific content)"
  },

  "priority_2b_integrity": {
    "report": "monitor/integrity/report-2026-05-28T01-18.json",
    "findings_count": 4,
    "stale_findings": 4,
    "new_iss_created": 0,
    "stale_log": [
      "Finding 0 [critical] ISS-2202 mech_a_bypass: STALE. Both entries in closed-issues.json have audit_grandfathered set (PROP-059-wiring-gap-2026-05-25-to-2026-05-26 and PROP-059-decider-step1d-and-priority3-leak-2026-05-26). Applied by prior decider run after integrity report timestamp.",
      "Finding 1 [critical] ISS-2203 mech_a_bypass: STALE. Same — both entries grandfathered.",
      "Finding 2 [critical] ISS-2207 mech_a_bypass: STALE. Entry has audit_grandfathered=PROP-059-decider-step1d-and-priority3-leak-2026-05-26, audit_grandfathered_at=2026-05-28T05:35:00Z (applied by decider run after the 01:18 integrity report).",
      "Finding 3 [moderate] EXP-433 expansion_tracker: STALE. EXP-433 is NOT in live tracker array (confirmed via tracker.items.find check); it IS in expansion-tracker-archive.jsonl. A prior decider run already moved it."
    ]
  },

  "priority_2c_rewrite_proposals": {
    "count": 2,
    "action": "skipped — both RW-001.json and RW-002.json have status=integrated"
  },

  "priority_3_curmudgeon_reviews": {
    "pending_at_digest": 3,
    "processed": [
      {
        "review": "WIN-006.c6.json",
        "trigger": "drift-audit (change-detected, verdict_length +21.2%)",
        "recommended_action": "minor_edit",
        "holes": [
          {"severity": "moderate", "iss": "ISS-2212", "action": "self-applied"},
          {"severity": "minor", "iss": "ISS-2213", "action": "self-applied"},
          {"severity": "minor", "iss": "ISS-2214", "action": "route-to-analyst (structural change across 4 WINs)"}
        ]
      },
      {
        "review": "SEC-4.2.4-EXP-434.c2.json",
        "queue_id": 409,
        "recommended_action": "no_change",
        "action": "popped (already archived at 2026-05-28T02:38Z by prior run; marked processed this run)"
      },
      {
        "review": "WIN-063.c8.json",
        "queue_id": 407,
        "recommended_action": "no_change",
        "action": "already popped (popped_by_queue_id=407 set); marked processed this run"
      }
    ]
  },

  "patches_applied": [
    {
      "iss_id": "ISS-2212",
      "win_id": "WIN-006",
      "field": "detail_verdict_text",
      "summary": "Boundary note genealogy: replaced 'all three sharing the same parent prediction (PROS-002)' with explicit dome-source citation showing PROS-002 arrows WIN-007/WIN-036 explicitly, WIN-006 standalone but mechanism label shared",
      "severity": "moderate"
    },
    {
      "iss_id": "ISS-2213",
      "win_id": "WIN-006",
      "field": "detail_verdict_text + tldr_verdict",
      "summary": "Replaced 'by any standard metric' with explicit three-convention enumeration (great-circle arc, longitude-only at NMP latitude, latitude-only; 1.0-5.2 km/yr vs 10-15 km/yr observed) in detail; 'angular-to-linear convention' in tldr",
      "severity": "minor"
    }
  ],

  "issues_created": ["ISS-2212 (moderate, closed-self-applied)", "ISS-2213 (minor, closed-self-applied)", "ISS-2214 (minor, routed-analyst as EXP-436)"],

  "bau_triage": {
    "processed": 0,
    "patched": 0,
    "wontfixed": 0,
    "escalated": 0,
    "routed_to_analyst": 0,
    "routed_to_curmudgeon": 0,
    "carry_over": [],
    "budget_used_pct": 5,
    "note": "0 open items with age >= 12h at triage time"
  },

  "m1_sweep": {
    "mode": "bau",
    "dryrun": false,
    "K_cap": 10,
    "candidates": 0,
    "acted": 0,
    "patched": 0,
    "narrow_patched": 0,
    "wontfixed": 0,
    "routed_to_analyst": 0,
    "routed_to_curmudgeon": 0,
    "escalated": 0,
    "skipped_recently_touched": 0,
    "iss_ids": []
  },

  "step_a0_normalization": {
    "stranded_closed_in_open": 0,
    "migrated": 0
  },

  "step_a0b_blocked_sweep": {
    "blocked_on_curmudgeon": 0,
    "migrated": 0
  },

  "curmudgeon_queue": {
    "mode": "bau",
    "depth": 0,
    "items": [],
    "current_schedule_interval_minutes": 240,
    "action_taken": "none"
  },

  "verify_on_read_outcomes": [
    {
      "source_review": "monitor/integrity/report-2026-05-28T01-18.json",
      "cited_file": "monitor/decisions/closed-issues.json",
      "cited_pattern": "ISS-2202/2203/2207 missing audit_grandfathered",
      "verified_at": "2026-05-28T14:40:08Z",
      "outcome": "STALE — all three entries now have audit_grandfathered fields applied by prior decider run"
    }
  ],

  "open_issues_final": 1,
  "open_issues_details": [
    {"id": "ISS-2214", "status": "assigned-analyst", "exp_id": "EXP-436", "severity": "minor"}
  ],

  "tests": "3692/3692 pass",

  "schedule_action_needed": null
}
