{
  "event": "push-failure",
  "timestamp": "2026-05-02T17:23:05Z",
  "error": "403 remote: Permission denied to Devilwench (both unified and split-push phases)",
  "diagnosis": "Split push diagnostic: both monitor/ phase and data+docs+predictions phase 403'd. Content-path is NOT the determinant. Environmental/IP issue. PAT has contents:write (per HNOTE-OPERATOR-PAT-DIAGNOSIS-CORRECTION-001). Universal-pusher rescue executed.",
  "files_synced_to_fuse": true,
  "universal_pusher_rescue": {
    "rescued_count": 13,
    "next_workspace_sync_window": "within 1h of this timestamp"
  },
  "split_push_diagnostic": {
    "phase_1_monitor_only_rc": "128",
    "phase_2_data_docs_predictions_rc": "128",
    "interpretation": "Both phases 403'd — NOT content-path; investigate IP/timing/heuristics"
  }
}
