{
  "run_id": "ws-sync-20260502T050451Z-2",
  "timestamp": "2026-05-02T05:05:13.847Z",
  "files_committed": 3,
  "skips_total": 6,
  "skip_breakdown": {
    "never_push": 0,
    "mtime_guard": 6
  },
  "agent_notes": "Routine run. 6 mtime-guard skips (all decider-committed-direct files where git is newer than FUSE — guard working as designed, no rescue needed). Zero never-push skips, zero strands. One new file committed: an analyst issue-proposal for pred105 tacit-withdrawal staging. Push succeeded first try; no fallback needed."
}