{
  "run_id": "ws-sync-2026-05-18T1657Z-13",
  "timestamp": "2026-05-18T16:57:14.659Z",
  "files_committed": 0,
  "skips_total": 43,
  "skip_breakdown": {
    "never_push": 0,
    "mtime_guard": 43
  },
  "json_gate_abort": true,
  "json_gate_abort_file": "monitor/decisions/daily-report-2026-05-18T09-21.json",
  "json_gate_abort_reason": "PLACEHOLDER text — not valid JSON",
  "agent_notes": "json-gate abort: daily-report-2026-05-18T09-21.json contained literal PLACEHOLDER text (not valid JSON). No data committed this cycle. Remaining new files (EXP-426, proposal-NEW, WIN-070.c5, daily-report-13-20, suggested-patches-13-20) were untouched — will retry next cycle. warning: decider left a placeholder report on FUSE."
}