{
  "last_run": "2026-04-11T05:00:00Z",
  "last_agent": "decider",
  "run_type": "Scheduled decider run",
  "mode": "Priority 1b (proposals already processed), Priority 3 (curmudgeon backfill+SEC6.4 reviews), standard processing",
  "status": "complete",
  "changes_pending_analysis": 0,
  "consecutive_quiet_polls": 8,
  "prev_decider_run": {
    "at": "2026-04-10T22:15:00Z",
    "note": "Prediction assessments Wave 3, ISS-710 created"
  },
  "patches_applied_this_run": {
    "wins": 0,
    "sections": 3,
    "infrastructure": 0,
    "data_files": 1
  },
  "issues_closed_this_run": 0,
  "issues_deferred_this_run": 0,
  "issues_created_this_run": 2,
  "open_issues": 15,
  "closed_issues": 598,
  "issues_assigned_analyst": 5,
  "issues_pending_human": 2,
  "curmudgeon_cycle": "churn-and-burn, queue depth 1 (PRED-batch-wave3 pending), 30min interval",
  "curmudgeon_last_review": "PRED-batch-backfill (processed and popped), SEC-6.4.c2 (processed)",
  "curmudgeon_queue_depth": 1,
  "pipeline_bugs": [
    "FUSE prevents deletion of processed proposal files (proposal-ISS-700/702-status.json) — already _processed, no functional impact",
    "workspace-sync gap: 30 PRED-assessment files in FUSE, 10 in git before this run"
  ],
  "external_reports": "Report-1 (Devilwench): ISS-698 wontfix (source field fixed). No new reports.",
  "integrity_status": "WARN (pre-existing false positives). 2969 tests pass.",
  "dome_site_status": "ACTIVE — V51.1 stable. 69 WINs, 94.5% accuracy. 8th consecutive quiet poll.",
  "build_needed": false,
  "build_note": "Build passing. 2969 tests. 3 sections.json patches applied. 4 predictions.json entries updated.",
  "human_notes_status": "0 pending notes",
  "priority_for_human": [
    "ISS-442: Verdict taxonomy restructuring — editorial decision needed",
    "ISS-710: Keywords meta tag expansion — approve or reject",
    "ISS-709 CLEARED: section 2b.7 cleared for publication (was critical blocker)"
  ],
  "fuse_staleness_events": [
    "SEC-part5-rewrite.c2.json was in workspace but not git clone — copied manually and popped from queue"
  ]
}